spring
fastdocgen
