Metadata-Version: 1.0
Name: spring
Version: 5.6.2
Summary: Simple Couchbase workload generator based on pylibcouchbase
Home-page: UNKNOWN
Author: Pavel Paulau
Author-email: pavel.paulau@gmail.com
License: UNKNOWN
Platform: UNKNOWN
